r53_ptr_vpc_associator/Associator.py
r53_ptr_vpc_associator/Utils.py
r53_ptr_vpc_associator/__init__.py
r53_ptr_vpc_associator/command.py
r53_ptr_vpc_associator-0.1.2.data/data/make_lambda_zip.sh
r53_ptr_vpc_associator-0.1.2.dist-info/LICENSE
r53_ptr_vpc_associator-0.1.2.dist-info/METADATA
r53_ptr_vpc_associator-0.1.2.dist-info/WHEEL
r53_ptr_vpc_associator-0.1.2.dist-info/entry_points.txt
r53_ptr_vpc_associator-0.1.2.dist-info/top_level.txt
r53_ptr_vpc_associator-0.1.2.dist-info/RECORD
