Metadata-Version: 2.1
Name: r53-ptr-vpc-associator
Version: 0.1.2
Summary: Associates route53 PTR records to particular vpc.
Home-page: https://github.com/rubelw/r53_ptr_vpc_associator
Author: Will Rubel
Author-email: willrubel@gmail.com
License: UNKNOWN
Keywords: aws,route53,vpc
Platform: any
Classifier: Development Status :: 4 - Beta
Classifier: Intended Audience :: Developers
Classifier: Natural Language :: English
Classifier: Operating System :: OS Independent
Classifier: Programming Language :: Python
Classifier: Programming Language :: Python
Classifier: Programming Language :: Python :: 3
Classifier: Programming Language :: Python :: 3.3
Classifier: Programming Language :: Python :: 3.4
Classifier: Programming Language :: Python :: 3.5
Classifier: Programming Language :: Python :: 3.6
Requires-Dist: boto3 (>=1.4.3)
Requires-Dist: requests (>=2.18)
Requires-Dist: Click (>=6.7)
Requires-Dist: configparser (>=3.5.0)
Requires-Dist: future (>=0.16.0)
Requires-Dist: six (>=1.11.0)
Requires-Dist: coverage (==4.0.3)
Requires-Dist: pip
